tracebook/__init__.py
tracebook/config.py
tracebook/dashboard.py
tracebook/decorators.py
tracebook/logger.py
tracebook/logger_core.py
tracebook/remote_handler.py
tracebook/utils.py
tracebook-0.1.10.dist-info/LICENSE
tracebook-0.1.10.dist-info/METADATA
tracebook-0.1.10.dist-info/WHEEL
tracebook-0.1.10.dist-info/top_level.txt
tracebook-0.1.10.dist-info/RECORD
