Metadata-Version: 2.1
Name: tracebook
Version: 0.1.10
Summary: A comprehensive code bookkeeping package
Author: Sujal Choudhari
Author-email: hello@sujal.xyz
Keywords: book-keeping,visualizer
Classifier: Programming Language :: Python :: 3
Classifier: License :: OSI Approved :: MIT License
Classifier: Programming Language :: Python :: 3.8
Requires-Python: >=3.6
License-File: LICENSE
Requires-Dist: blinker==1.8.2
Requires-Dist: certifi==2024.7.4
Requires-Dist: charset-normalizer==3.3.2
Requires-Dist: click==8.1.7
Requires-Dist: colorama==0.4.6
Requires-Dist: dash==2.17.1
Requires-Dist: dash-bootstrap-components==1.6.0
Requires-Dist: dash-core-components==2.0.0
Requires-Dist: dash-html-components==2.0.0
Requires-Dist: dash-table==5.0.0
Requires-Dist: docutils==0.21.2
Requires-Dist: Flask==3.0.3
Requires-Dist: idna==3.7
Requires-Dist: importlib-metadata==8.2.0
Requires-Dist: itsdangerous==2.2.0
Requires-Dist: jaraco.classes==3.4.0
Requires-Dist: jaraco.context==5.3.0
Requires-Dist: jaraco.functools==4.0.2
Requires-Dist: Jinja2==3.1.4
Requires-Dist: keyring==25.3.0
Requires-Dist: markdown-it-py==3.0.0
Requires-Dist: MarkupSafe==2.1.5
Requires-Dist: mdurl==0.1.2
Requires-Dist: more-itertools==10.4.0
Requires-Dist: nest-asyncio==1.6.0
Requires-Dist: nh3==0.2.18
Requires-Dist: packaging==24.1
Requires-Dist: pkginfo==1.10.0
Requires-Dist: plotly==5.23.0
Requires-Dist: psutil==6.0.0
Requires-Dist: Pygments==2.18.0
Requires-Dist: pywin32-ctypes==0.2.2
Requires-Dist: readme-renderer==44.0
Requires-Dist: requests==2.32.3
Requires-Dist: requests-toolbelt==1.0.0
Requires-Dist: retrying==1.3.4
Requires-Dist: rfc3986==2.0.0
Requires-Dist: rich==13.7.1
Requires-Dist: setuptools==72.1.0
Requires-Dist: six==1.16.0
Requires-Dist: tenacity==9.0.0
Requires-Dist: typing-extensions==4.12.2
Requires-Dist: urllib3==2.2.2
Requires-Dist: watchdog==4.0.2
Requires-Dist: Werkzeug==3.0.3
Requires-Dist: wheel==0.44.0
Requires-Dist: zipp==3.20.0
